    {
        "name": "BAG_ITS001",
        "title": "BAG 1 Keuze te starten BAG-proces",
        "display": "wizard",
        "components": [
            {
                "label": "Start van het BAG-proces",
                "type": "panel",
                "key": "BAG_ITS001_SN001",
                "title": "Start van het BAG-proces",
                "input": false,
                "breadcrumbClickable": true,
                "buttonSettings": {
                    "next": true,
                    "previous": false,
                    "cancel": true
                },
                "components": [
                    {
                        "html": "<h2>Start van het BAG-proces</h2>",
                        "label": "Start van het BAG-proces",
                        "refreshOnChange": false,
                        "key": "HF_StartBagProces",
                        "type": "content",
                        "input": false,
                        "tableView": false
                    },
                    {
                        "label": "Welk proces moet er worden gestart:",
                        "type": "selectboxes",
                        "key": "CB_TeStartenProces",
                        "input": true,
                        "optionsLabelPosition": "right",
                        "inline": false,
                        "inputType": "checkbox",
                        "values": [
                            {
                                "label": "Nummerbeschikking-Tekenaar",
                                "value": "nummerbeschikkingTekenaar"
                            },
                            {
                                "label": "Nummerbeschikking-Ondertekenaar",
                                "value": "nummerbeschikkingOndertekenaar"
                            },
                            {
                                "label": "Schriftelijke verklaring",
                                "value": "schriftelijkeVerklaring"
                            }
                        ],
                        "validate": {
                            "required": true
                        }
                    },
                    {
                        "label": "Toegevoegde documenten:",
                        "type": "selectboxes",
                        "key": "CB_ToegevoegdeDocumenten",
                        "input": true,
                        "optionsLabelPosition": "right",
                        "inline": false,
                        "inputType": "checkbox",
                        "values": [
                            {
                                "label": "Nummerbeschikking",
                                "value": "nummerbeschikking"
                            },
                            {
                                "label": "Schriftelijke verklaring-Ambtelijke correctie",
                                "value": "schriftelijkeVerklaringAmbtelijkeCorrectie"
                            },
                            {
                                "label": "Schriftelijke verklaring-Proces verbaal van constatering",
                                "value": "schriftelijkeVerklaringProcesVerbaalVanConstatering"
                            },
                            {
                                "label": "Schriftelijke verklaring-Wijziging t.b.v. een goede registratie",
                                "value": "schriftelijkeVerklaringWijzigingTBVEenGoedeRegistratie"
                            },
                            {
                                "label": "Postcodebeschikking",
                                "value": "postcodebeschikking"
                            },
                            {
                                "label": "Tekening",
                                "value": "tekening"
                            }
                        ]
                    }
                ]
            },
            {
                "label": "Aanvullen en toewijzen",
                "type": "panel",
                "key": "BAG_ITS001_SN002",
                "title": "Aanvullen en toewijzen",
                "input": false,
                "breadcrumbClickable": true,
                "buttonSettings": {
                    "next": false,
                    "previous": true,
                    "cancel": true
                },
                "components": [
                    {
                        "html": "<h2>Toelichting en toewijzing</h2>",
                        "label": "HF_ToelichtingToewijzen",
                        "refreshOnChange": false,
                        "key": "HF_ToelichtingToewijzen",
                        "type": "content",
                        "input": false,
                        "tableView": false
                    },
                    {
                        "label": "<b>Reden van starten proces nummerbeschikking:</b>",
                        "widget": "html5",
                        "tableView": true,
                        "data": {
                            "values": [
                                {
                                    "label": "Verleende vergunning",
                                    "value": "verleendeVergunning"
                                },
                                {
                                    "label": "Terugmelding",
                                    "value": "terugmelding"
                                }
                            ]
                        },
                        "validate": {
                            "required": true
                        },
                        "validateWhenHidden": false,
                        "key": "CO_RedenStartNummerbeschikking",
                        "type": "select",
                        "input": true,
                        "conditional": {
                            "show": true,
                            "conjunction": "any",
                            "conditions": [
                                {
                                    "component": "CB_TeStartenProces",
                                    "operator": "isEqual",
                                    "value": "nummerbeschikkingOndertekenaar"
                                },
                                {
                                    "component": "CB_TeStartenProces",
                                    "operator": "isEqual",
                                    "value": "nummerbeschikkingTekenaar"
                                }
                            ]
                        }
                    },
                    {
                        "label": "Toelichting nummerbeschikking aan tekenaar:",
                        "type": "textarea",
                        "key": "TA_ToelichtingNummerBeschikkingTekenaar",
                        "input": true,
                        "autoExpand": false,
                        "validate": {
                            "required": true
                        },
                        "conditional": {
                            "show": true,
                            "conjunction": "any",
                            "conditions": [
                                {
                                    "component": "CB_TeStartenProces",
                                    "operator": "isEqual",
                                    "value": "nummerbeschikkingTekenaar"
                                }
                            ]
                        }
                    },
                    {
                        "html": "</br>Toewijzen aan tekenaar:",
                        "label": "Toewijzen aan tekenaar",
                        "refreshOnChange": false,
                        "key": "HF_ToewijzenTekenaar",
                        "type": "content",
                        "input": false,
                        "tableView": false,
                        "conditional": {
                            "show": true,
                            "conjunction": "any",
                            "conditions": [
                                {
                                    "component": "CB_TeStartenProces",
                                    "operator": "isEqual",
                                    "value": "nummerbeschikkingTekenaar"
                                }
                            ]
                        }
                    },
                    {
                        "type": "groepMedewerkerFieldset",
                        "key": "AG_Tekenaar",
                        "label": "Toewijzen aan tekenaar:",
                        "input": false,
                        "components": [
                            {
                                "label": "Groep",
                                "type": "select",
                                "key": "AG_Tekenaar_Groep",
                                "input": true,
                                "widget": "html5",
                                "dataSrc": "custom",
                                "clearOnRefresh": true,
                                "validate": {
                                    "required": true
                                }
                            },
                            {
                                "label": "Medewerker",
                                "type": "select",
                                "key": "AG_Tekenaar_Medewerker",
                                "widget": "html5",
                                "input": true,
                                "dataSrc": "custom",
                                "refreshOn": "AG_Tekenaar_Groep",
                                "clearOnRefresh": true,
                                "validate": {
                                    "required": true
                                }
                            }
                        ],
                        "conditional": {
                            "show": true,
                            "conjunction": "any",
                            "conditions": [
                                {
                                    "component": "CB_TeStartenProces",
                                    "operator": "isEqual",
                                    "value": "nummerbeschikkingTekenaar"
                                }
                            ]
                        }
                    },
                    {
                        "label":"<br/><br/><b>Toelichting opdracht uitzetten bij ondertekenaar:</b>",
                        "type": "textarea",
                        "key": "TA_ToelichtingNummerbeschikkingOndertekenaar",
                        "input": true,
                        "autoExpand": false,
                        "validate": {
                            "required": true
                        },
                        "conditional": {
                            "show": true,
                            "conjunction": "any",
                            "conditions": [
                                {
                                    "component": "CB_TeStartenProces",
                                    "operator": "isEqual",
                                    "value": "nummerbeschikkingOndertekenaar"
                                }
                            ]
                        }
                    },
                    {
                        "html": "</br>Toewijzen aan ondertekenaar:",
                        "label": "Toewijzen aan ondertekenaar",
                        "refreshOnChange": false,
                        "key": "HF_ToewijzenOndertekenaar",
                        "type": "content",
                        "input": false,
                        "tableView": false,
                        "conditional": {
                            "show": true,
                            "conjunction": "any",
                            "conditions": [
                                {
                                    "component": "CB_TeStartenProces",
                                    "operator": "isEqual",
                                    "value": "nummerbeschikkingOndertekenaar"
                                }
                            ]
                        }
                    },
                    {
                        "type": "groepMedewerkerFieldset",
                        "key": "AG_OndertekenaarNummerBeschikking",
                        "label": "Toewijzen aan ondertekenaar:",
                        "input": false,
                        "components": [
                            {
                                "label": "Groep",
                                "type": "select",
                                "key": "AG_OndertekenaarNummerBeschikking_Groep",
                                "input": true,
                                "widget": "html5",
                                "dataSrc": "custom",
                                "clearOnRefresh": true,
                                "validate": {
                                    "required": true
                                }
                            },
                            {
                                "label": "Medewerker",
                                "type": "select",
                                "key": "AG_OndertekenaarNummerBeschikking_Medewerker",
                                "widget": "html5",
                                "input": true,
                                "dataSrc": "custom",
                                "refreshOn": "AG_OndertekenaarNummerBeschikking_Groep",
                                "clearOnRefresh": true,
                                "validate": {
                                    "required": true
                                }
                            }
                        ],
                        "conditional": {
                            "show": true,
                            "conjunction": "any",
                            "conditions": [
                                {
                                    "component": "CB_TeStartenProces",
                                    "operator": "isEqual",
                                    "value": "nummerbeschikkingOndertekenaar"
                                }
                            ]
                        }
                    },
                    {
                        "label": "<br/><br/><b>Reden van starten proces schriftelijke verklaring:</b>",
                        "widget": "html5",
                        "tableView": true,
                        "data": {
                            "values": [
                                {
                                    "label": "Terugmelding",
                                    "value": "terugmelding"
                                },
                                {
                                    "label": "Gemiste wettelijke termijn",
                                    "value": "gemisteWettelijkeTermijn"
                                }
                            ]
                        },
                        "validate": {
                            "required": true
                        },
                        "validateWhenHidden": false,
                        "key": "CO_RedenStartSchriftelijkeVerklaring",
                        "type": "select",
                        "input": true,
                        "conditional": {
                            "show": true,
                            "conjunction": "any",
                            "conditions": [
                                {
                                    "component": "CB_TeStartenProces",
                                    "operator": "isEqual",
                                    "value": "schriftelijkeVerklaring"
                                }
                            ]
                        }
                    },
                    {
                        "label": "Toelichting schriftelijke verklaring:",
                        "type": "textarea",
                        "key": "TA_ToelichtingSchriftelijkeVerklaring",
                        "input": true,
                        "autoExpand": false,
                        "validate": {
                            "required": true
                        },
                        "conditional": {
                            "show": true,
                            "conjunction": "any",
                            "conditions": [
                                {
                                    "component": "CB_TeStartenProces",
                                    "operator": "isEqual",
                                    "value": "schriftelijkeVerklaring"
                                }
                            ]
                        }
                    },
                    {
                        "html": "</br>Toewijzing opdracht schriftelijke verklaring uitzetten bij ondertekenaar:",
                        "label": "Toewijzing opdracht schriftelijke verklaring uitzetten bij ondertekenaar",
                        "refreshOnChange": false,
                        "key": "HF_OndertekenaarSchriftelijkeVerklaring",
                        "type": "content",
                        "input": false,
                        "tableView": false,
                        "conditional": {
                            "show": true,
                            "conjunction": "any",
                            "conditions": [
                                {
                                    "component": "CB_TeStartenProces",
                                    "operator": "isEqual",
                                    "value": "schriftelijkeVerklaring"
                                }
                            ]
                        }
                    },
                    {
                        "type": "groepMedewerkerFieldset",
                        "key": "AG_OndertekenaarSchriftelijkeVerklaring",
                        "label": "Toewijzing opdracht schriftelijke verklaring uitzetten bij ondertekenaar:",
                        "input": false,
                        "components": [
                            {
                                "label": "Groep",
                                "type": "select",
                                "key": "AG_OndertekenaarSchriftelijkeVerklaring_Groep",
                                "input": true,
                                "widget": "html5",
                                "dataSrc": "custom",
                                "clearOnRefresh": true,
                                "validate": {
                                    "required": true
                                }
                            },
                            {
                                "label": "Medewerker",
                                "type": "select",
                                "key": "AG_OndertekenaarSchriftelijkeVerklaring_Medewerker",
                                "widget": "html5",
                                "input": true,
                                "dataSrc": "custom",
                                "refreshOn": "AG_OndertekenaarSchriftelijkeVerklaring_Groep",
                                "clearOnRefresh": true,
                                "validate": {
                                    "required": true
                                }
                            }
                        ],
                        "conditional": {
                            "show": true,
                            "conjunction": "any",
                            "conditions": [
                                {
                                    "component": "CB_TeStartenProces",
                                    "operator": "isEqual",
                                    "value": "schriftelijkeVerklaring"
                                }
                            ]
                        }
                    }
                ]
            }
        ]
    }